{
  "vendor": "OTODOM",
  "baseUrl": "https://www.otodom.pl",
  "offerUrlXpath": "//*[@id=\"body-container\"]/div/div/div[1]/div/article/@data-url",
  "addressXpath": "//a[@href=\"#map\"]",
  "imageXpath": "//*[@id=\"root\"]/div/article/section/div[1]/div/div[1]/div/div[2]/div/div[2]/div/picture/img/@src",
  "areaXpath": "//*[@id=\"root\"]/div/article/div/div[1]/section[1]/div/ul/li[starts-with(text(), \"Powierzchnia:\")]/strong",
  "priceXpath": "//*[@id=\"root\"]/div/article/header//div[contains(text(), \"zł\")]",
  "numberOfRoomsXpath": "//*[@id=\"root\"]/div/article/div/div[1]/section[1]/div/ul/li[starts-with(text(), \"Liczba pokoi:\")]/strong",
  "floorXpath": "//*[@id=\"root\"]/div/article/div/div[1]/section[1]/div/ul/li[starts-with(text(), \"Piętro:\")]/strong",
  "yearOfConstructionXpath": "//*[@id=\"root\"]/div/article/div/div[1]/section[1]/div/ul/li[starts-with(text(), \"Rok budowy:\")]/strong",
  "titleXpath": "//*[@id=\"root\"]/div/article/header/div[1]//h1",
  "pageParam": "&page=",
  "pagesToVisit": 10,
  "concurrentRequestsCount": 30,
  "requestDelay": 20000,
  "pages": [
    {
      "offerType": "RENT",
      "propertyType": "HOUSE",
      "url": "/wynajem/dom/?nrAdsPerPage=72"
    },
    {
      "offerType": "RENT",
      "propertyType": "FLAT",
      "url": "/wynajem/mieszkanie/?nrAdsPerPage=72"
    },
    {
      "offerType": "SELL",
      "propertyType": "FLAT",
      "url": "/sprzedaz/mieszkanie/?nrAdsPerPage=72"
    },
    {
      "offerType": "SELL",
      "propertyType": "HOUSE",
      "url": "/sprzedaz/dom/?nrAdsPerPage=72"
    }
  ]
}
